ib_excel_formatting.py
ib_excel_formatting-0.1.0.dist-info/METADATA
ib_excel_formatting-0.1.0.dist-info/WHEEL
ib_excel_formatting-0.1.0.dist-info/licenses/LICENSE
ib_excel_formatting-0.1.0.dist-info/RECORD
