Metadata-Version: 2.4
Name: ib-excel-formatting
Version: 0.1.0
Summary: Check and apply IB Excel formatting conventions (black=formulas, blue=hardcoded, green=cross-sheet, red=external/provider)
Project-URL: Homepage, https://github.com/daaa1m/ib-excel-formatting
Project-URL: Repository, https://github.com/daaa1m/ib-excel-formatting
License-Expression: MIT
License-File: LICENSE
Keywords: excel,finance,formatting,investment-banking,openpyxl
Classifier: Development Status :: 4 - Beta
Classifier: Intended Audience :: Financial and Insurance Industry
Classifier: License :: OSI Approved :: MIT License
Classifier: Operating System :: OS Independent
Classifier: Programming Language :: Python :: 3
Classifier: Programming Language :: Python :: 3.10
Classifier: Programming Language :: Python :: 3.11
Classifier: Programming Language :: Python :: 3.12
Classifier: Topic :: Office/Business :: Financial :: Spreadsheet
Requires-Python: >=3.10
Requires-Dist: openpyxl>=3.1.5
